daiquiry/__init__.py
daiquiry/formatter.py
daiquiry/handlers.py
daiquiry/output.py
daiquiry/py.typed
daiquiry/types.py
daiquiry/tests/__init__.py
daiquiry/tests/test_daiquiry.py
daiquiry/tests/test_formatter.py
daiquiry/tests/test_output.py
daiquiry-3.2.5.dist-info/LICENSE
daiquiry-3.2.5.dist-info/METADATA
daiquiry-3.2.5.dist-info/WHEEL
daiquiry-3.2.5.dist-info/top_level.txt
daiquiry-3.2.5.dist-info/RECORD
